<?xml version="1.0" encoding="UTF-8"?>
<schemalist>
  <enum id='com.deepin.dde.GDesktopBackgroundStyle'>
    <value nick='none' value='0'/>
    <value nick='wallpaper' value='1'/>
    <value nick='centered' value='2'/>
    <value nick='scaled' value='3'/>
    <value nick='stretched' value='4'/>
    <value nick='zoom' value='5'/>
    <value nick='spanned' value='6'/>
  </enum>
  <enum id='com.deepin.dde.GDesktopBackgroundShading'>
    <value nick='solid' value='0'/>
    <value nick='vertical' value='1'/>
    <value nick='horizontal' value='2'/>
  </enum>

  <schema path="/com/deepin/dde/personalization/" id="com.deepin.dde.personalization" gettext-domain="DDE">
    <!-- custom keys for deepin -->
    <key type="s" name="current-theme">
      <default>'Deepin'</default>
      <summary>Current Theme</summary>
      <description>Current System Theme</description>
    </key>
    <key type="s" name="current-sound-theme">
      <default>'LinuxDeepin'</default>
      <summary>Current Sound Theme</summary>
      <description>Current System Sound Theme</description>
    </key>
    <key type="s" name="greeter-theme">
      <default>'sky'</default>
      <summary>theme of greeter and lock</summary>
      <description>the theme of greeter and lock</description>
    </key>

    <!-- copy from org.gnome.desktop.background.gschema -->
    <key type="b" name="draw-background">
      <default>true</default>
      <summary>Draw Desktop Background</summary>
      <description>Have GNOME draw the desktop background. DEPRECATED: This key is deprecated and ignored.</description>
    </key>
    <key name="picture-options" enum="com.deepin.dde.GDesktopBackgroundStyle">
      <default>'zoom'</default>
      <summary>Picture Options</summary>
      <description>Determines how the image set by wallpaper_filename is rendered. Possible values are "none", "wallpaper", "centered", "scaled", "stretched", "zoom", "spanned".</description>
    </key>
    <key type="s" name="picture-uri">
      <default>'file:///usr/share/backgrounds/default_background.jpg'</default>
      <summary>Picture URI</summary>
      <description>URI to use for the background image. Note that the backend only supports local (file://) URIs.</description>
    </key>
    <key type="i" name="picture-opacity">
      <range min="0" max="100"/>
      <default>100</default>
      <summary>Picture Opacity</summary>
      <description>Opacity with which to draw the background picture.</description>
    </key>
    <key type="s" name="primary-color">
      <default>'#000000'</default>
      <summary>Primary Color</summary>
      <description>Left or Top color when drawing gradients, or the solid color.</description>
    </key>
    <key type="s" name="secondary-color">
      <default>'#023c88'</default>
      <summary>Secondary Color</summary>
      <description>Right or Bottom color when drawing gradients, not used for solid color.</description>
    </key>
    <key name="color-shading-type" enum="com.deepin.dde.GDesktopBackgroundShading">
      <default>'solid'</default>
      <summary>Color Shading Type</summary>
      <description>How to shade the background color. Possible values are "horizontal", "vertical", and "solid".</description>
    </key>
    <key type="b" name="show-desktop-icons">
      <default>false</default>
      <summary>Have file manager handle the desktop</summary>
      <description>If set to true, then file manager will draw the icons on the desktop.</description>
    </key>
  </schema>
</schemalist>
